orchespy/__init__.py
orchespy/decorator.py
orchespy/numpy.py
orchespy/transfer.py
orchespy/devicetype/__init__.py
orchespy/devicetype/base.py
orchespy/devicetype/cuda.py
orchespy/devicetype/find_device_class.py
orchespy/devicetype/host.py
orchespy/devicetype/ve.py
orchespy/devicetype/_transfer/__init__.py
orchespy/devicetype/_transfer/cunlc.cpython-38-x86_64-linux-gnu.so
orchespy-0.2.0b2.dist-info/LICENSE
orchespy-0.2.0b2.dist-info/METADATA
orchespy-0.2.0b2.dist-info/WHEEL
orchespy-0.2.0b2.dist-info/top_level.txt
orchespy-0.2.0b2.dist-info/RECORD
