Metadata-Version: 2.1
Name: orchespy
Version: 0.2.0b2
Summary: Device-independent library for NumPy programs
Home-page: https://github.com/SX-Aurora/orchespy/
Author: NEC
Author-email: dev-nlcpy@sxarr.jp.nec.com
License: BSD 3-Clause
License-File: LICENSE
